resolver/__init__.py
resolver/exceptions.py
resolver/kms.py
sceptre_kms_resolver-1.0.2.dist-info/METADATA
sceptre_kms_resolver-1.0.2.dist-info/WHEEL
sceptre_kms_resolver-1.0.2.dist-info/entry_points.txt
sceptre_kms_resolver-1.0.2.dist-info/top_level.txt
sceptre_kms_resolver-1.0.2.dist-info/RECORD
